tcdd_bilet_kontrol/__init__.py
tcdd_bilet_kontrol/requirements.txt
tcdd_bilet_kontrol/Assets/Logo.png
tcdd_bilet_kontrol/Assets/favicon.ico
tcdd_bilet_kontrol/Assets/favicon.png
tcdd_bilet_kontrol/Assets/index.html
tcdd_bilet_kontrol/Assets/manifest.json
tcdd_bilet_kontrol/Assets/icons/apple-touch-icon-192.png
tcdd_bilet_kontrol/Assets/icons/icon-192.png
tcdd_bilet_kontrol/Assets/icons/icon-512.png
tcdd_bilet_kontrol/Assets/icons/icon-maskable-192.png
tcdd_bilet_kontrol/Assets/icons/icon-maskable-512.png
tcdd_bilet_kontrol/Assets/icons/loading-animation.png
tcdd_bilet_kontrol/CLI/__init__.py
tcdd_bilet_kontrol/Layouts/KekikFlet.py
tcdd_bilet_kontrol/Layouts/Panel.py
tcdd_bilet_kontrol/Layouts/__init__.py
tcdd_bilet_kontrol/Libs/List2DT.py
tcdd_bilet_kontrol/Libs/TCDD_Selenium.py
tcdd_bilet_kontrol/Libs/__init__.py
tcdd_bilet_kontrol-0.6.data/data/share/appdata/org.kekikakademi.tcdd_bilet_kontrol.appdata.xml
tcdd_bilet_kontrol-0.6.data/data/share/applications/org.kekikakademi.tcdd_bilet_kontrol.desktop
tcdd_bilet_kontrol-0.6.data/data/share/icons/hicolor/scalable/apps/Logo.png
tcdd_bilet_kontrol-0.6.dist-info/LICENSE
tcdd_bilet_kontrol-0.6.dist-info/METADATA
tcdd_bilet_kontrol-0.6.dist-info/WHEEL
tcdd_bilet_kontrol-0.6.dist-info/entry_points.txt
tcdd_bilet_kontrol-0.6.dist-info/top_level.txt
tcdd_bilet_kontrol-0.6.dist-info/RECORD
