Metadata-Version: 2.1
Name: tcdd-bilet-kontrol
Version: 0.6
Summary: TCDD Bilet Kontrol Etme Arayüzü
Home-page: https://github.com/keyiflerolsun/tcdd_bilet_kontrol
Author: keyiflerolsun
Author-email: keyiflerolsun@gmail.com
License: GPLv3+
Keywords: tcdd_bilet_kontrol,KekikAkademi,keyiflerolsun
Classifier: Development Status :: 5 - Production/Stable
Classifier: License :: OSI Approved :: GNU General Public License v3 or later (GPLv3+)
Classifier: Programming Language :: Python :: 3
Requires-Python: >=3.10
License-File: LICENSE
Requires-Dist: pip
Requires-Dist: setuptools
Requires-Dist: wheel
Requires-Dist: Kekik
Requires-Dist: SelSik
Requires-Dist: flet
Requires-Dist: pandas
Requires-Dist: regex
Requires-Dist: tabulate
Requires-Dist: notify-py
